customizable/__init__.py
customizable/config.py
customizable-0.1.3.dist-info/LICENSE
customizable-0.1.3.dist-info/METADATA
customizable-0.1.3.dist-info/WHEEL
customizable-0.1.3.dist-info/top_level.txt
customizable-0.1.3.dist-info/RECORD
